AbuLianghuaKetang/README.md
AbuLianghuaKetang/__init__.py
AbuLianghuaKetang/__main__.py
AbuLianghuaKetang/file.epub
AbuLianghuaKetang/index.html
AbuLianghuaKetang/css/__init__.py
AbuLianghuaKetang/css/annotations.css
AbuLianghuaKetang/css/main.css
AbuLianghuaKetang/css/normalize.css
AbuLianghuaKetang/css/popup.css
AbuLianghuaKetang/font/__init__.py
AbuLianghuaKetang/font/fontello.eot
AbuLianghuaKetang/font/fontello.svg
AbuLianghuaKetang/font/fontello.ttf
AbuLianghuaKetang/font/fontello.woff
AbuLianghuaKetang/img/__init__.py
AbuLianghuaKetang/img/annotator-glyph-sprite.png
AbuLianghuaKetang/img/annotator-icon-sprite.png
AbuLianghuaKetang/img/apple-touch-icon.png
AbuLianghuaKetang/img/cancelfullscreen.png
AbuLianghuaKetang/img/close.png
AbuLianghuaKetang/img/fullscreen.png
AbuLianghuaKetang/img/loader.gif
AbuLianghuaKetang/img/menu-icon.png
AbuLianghuaKetang/img/save.png
AbuLianghuaKetang/img/saved.png
AbuLianghuaKetang/img/settings-s.png
AbuLianghuaKetang/img/settings.png
AbuLianghuaKetang/img/star.png
AbuLianghuaKetang/js/__init__.py
AbuLianghuaKetang/js/epub.js
AbuLianghuaKetang/js/epub.min.js
AbuLianghuaKetang/js/epub.min.map
AbuLianghuaKetang/js/hooks.min.js
AbuLianghuaKetang/js/hooks.min.map
AbuLianghuaKetang/js/reader.js
AbuLianghuaKetang/js/reader.js.map
AbuLianghuaKetang/js/reader.min.js
AbuLianghuaKetang/js/reader.min.map
AbuLianghuaKetang/js/hooks/__init__.py
AbuLianghuaKetang/js/hooks/extensions/__init__.py
AbuLianghuaKetang/js/hooks/extensions/highlight.js
AbuLianghuaKetang/js/libs/__init__.py
AbuLianghuaKetang/js/libs/jquery.min.js
AbuLianghuaKetang/js/libs/localforage.min.js
AbuLianghuaKetang/js/libs/screenfull.js
AbuLianghuaKetang/js/libs/screenfull.min.js
AbuLianghuaKetang/js/libs/zip.min.js
AbuLianghuaKetang/js/plugins/__init__.py
AbuLianghuaKetang/js/plugins/hypothesis.js
AbuLianghuaKetang/js/plugins/search.js
abu_lianghua_ketang-2024.3.2.0.dist-info/METADATA
abu_lianghua_ketang-2024.3.2.0.dist-info/WHEEL
abu_lianghua_ketang-2024.3.2.0.dist-info/entry_points.txt
abu_lianghua_ketang-2024.3.2.0.dist-info/top_level.txt
abu_lianghua_ketang-2024.3.2.0.dist-info/RECORD
